aestool/__init__.py
aestool/aestool.py
aestool-0.0.1.dist-info/LICENSE
aestool-0.0.1.dist-info/METADATA
aestool-0.0.1.dist-info/WHEEL
aestool-0.0.1.dist-info/entry_points.txt
aestool-0.0.1.dist-info/top_level.txt
aestool-0.0.1.dist-info/RECORD
