Metadata-Version: 2.1
Name: aestool
Version: 0.0.1
Summary: A simple AES encryption and decryption tool
Home-page: https://github.com/babaralijamali/aestool
Author: Babar Ali Jamali
Author-email: babar995@gmail.com
Classifier: Programming Language :: Python :: 3
Classifier: License :: OSI Approved :: MIT License
Classifier: Operating System :: OS Independent
Requires-Python: >=3.6
License-File: LICENSE
Requires-Dist: pycryptodome
